biosage_terminal/__init__.py
biosage_terminal/ai.py
biosage_terminal/app.py
biosage_terminal/cli.py
biosage_terminal/components.py
biosage_terminal/models.py
biosage_terminal/storage.py
biosage_terminal/styles.tcss
biosage_terminal/theme.py
biosage_terminal/screens/__init__.py
biosage_terminal/screens/admin_audit.py
biosage_terminal/screens/case_view.py
biosage_terminal/screens/cases_manager.py
biosage_terminal/screens/collaboration_room.py
biosage_terminal/screens/dashboard.py
biosage_terminal/screens/diagnosis_progress.py
biosage_terminal/screens/diagnosis_result.py
biosage_terminal/screens/evidence.py
biosage_terminal/screens/help.py
biosage_terminal/screens/model_operations.py
biosage_terminal/screens/onboarding.py
biosage_terminal/screens/patient_summary.py
biosage_terminal/screens/research_hub.py
biosage_terminal/screens/specialists.py
biosage_terminal/screens/tests_orders.py
biosage_terminal/screens/visual_diagnosis.py
biosage_terminal/screens/welcome.py
biosage_terminal-2.1.1.dist-info/METADATA
biosage_terminal-2.1.1.dist-info/WHEEL
biosage_terminal-2.1.1.dist-info/entry_points.txt
biosage_terminal-2.1.1.dist-info/top_level.txt
biosage_terminal-2.1.1.dist-info/RECORD
