Metadata-Version: 2.4
Name: biosage-terminal
Version: 2.1.1
Summary: BioSage - AI-Powered Medical Diagnostic Assistant TUI with ARGUS Debate Framework
Author-email: BioSage Team <team@biosage.ai>
Maintainer-email: BioSage Team <team@biosage.ai>
License: MIT
Project-URL: Homepage, https://github.com/biosage/biosage-terminal
Project-URL: Documentation, https://biosage.ai/docs
Project-URL: Repository, https://github.com/biosage/biosage-terminal
Project-URL: Bug Tracker, https://github.com/biosage/biosage-terminal/issues
Project-URL: Changelog, https://github.com/biosage/biosage-terminal/blob/main/CHANGELOG.md
Keywords: medical,diagnosis,ai,tui,terminal,healthcare,argus,debate-framework,bayesian,clinical-decision-support,medical-ai,multi-agent,llm,evidence-based-medicine
Classifier: Development Status :: 5 - Production/Stable
Classifier: Environment :: Console
Classifier: Environment :: Console :: Curses
Classifier: Intended Audience :: Healthcare Industry
Classifier: Intended Audience :: Developers
Classifier: Intended Audience :: Science/Research
Classifier: License :: OSI Approved :: MIT License
Classifier: Operating System :: OS Independent
Classifier: Operating System :: Microsoft :: Windows
Classifier: Operating System :: MacOS
Classifier: Operating System :: POSIX :: Linux
Classifier: Programming Language :: Python :: 3
Classifier: Programming Language :: Python :: 3.11
Classifier: Programming Language :: Python :: 3.12
Classifier: Programming Language :: Python :: 3.13
Classifier: Programming Language :: Python :: 3 :: Only
Classifier: Topic :: Scientific/Engineering :: Medical Science Apps.
Classifier: Topic :: Scientific/Engineering :: Artificial Intelligence
Classifier: Topic :: Terminals
Classifier: Typing :: Typed
Requires-Python: >=3.11
Requires-Dist: textual>=0.47.0
Requires-Dist: rich>=13.7.0
Requires-Dist: argus-debate-ai>=1.0.0
Requires-Dist: pydantic>=2.5.0
Requires-Dist: python-dotenv>=1.0.0
Requires-Dist: plotext>=5.2.8
Requires-Dist: aiofiles>=23.2.1
Requires-Dist: httpx>=0.27.0
Requires-Dist: pyfiglet>=1.0.0
Provides-Extra: dev
Requires-Dist: pytest>=7.4.0; extra == "dev"
Requires-Dist: pytest-asyncio>=0.23.0; extra == "dev"
Requires-Dist: pytest-cov>=4.1.0; extra == "dev"
Requires-Dist: black>=24.0.0; extra == "dev"
Requires-Dist: ruff>=0.1.0; extra == "dev"
Requires-Dist: mypy>=1.8.0; extra == "dev"
Requires-Dist: build>=1.0.0; extra == "dev"
Requires-Dist: twine>=5.0.0; extra == "dev"
Provides-Extra: gemini
Requires-Dist: google-generativeai>=0.8.0; extra == "gemini"
Provides-Extra: openai
Requires-Dist: openai>=1.40.0; extra == "openai"
Provides-Extra: anthropic
Requires-Dist: anthropic>=0.34.0; extra == "anthropic"
Provides-Extra: groq
Requires-Dist: groq>=0.10.0; extra == "groq"
Provides-Extra: mistral
Requires-Dist: mistralai>=1.0.0; extra == "mistral"
Provides-Extra: cohere
Requires-Dist: cohere>=5.9.0; extra == "cohere"
Provides-Extra: all-llms
Requires-Dist: google-generativeai>=0.8.0; extra == "all-llms"
Requires-Dist: openai>=1.40.0; extra == "all-llms"
Requires-Dist: anthropic>=0.34.0; extra == "all-llms"
Requires-Dist: groq>=0.10.0; extra == "all-llms"
Requires-Dist: mistralai>=1.0.0; extra == "all-llms"
Requires-Dist: cohere>=5.9.0; extra == "all-llms"
